{"title":"Weverse Magazine ─ FEATURE","url":"https://magazine.weverse.io/article/list?lang=ko&colca=6","favicon":"https://ssl.pstatic.net/static/wevweb/public/favicon.ico","elements":[{"title":"사쿠라의 게임 생활","contents":"2023.12.11","link":"https://magazine.weverse.io/article/view?lang=ko&colca=6&artist=&searchword=&num=959","retrieved":1702264148867,"image":"https://cdn-contents.magazine.weverse.io/upload/img/202312/20231208TIFeGeXd62.jpg"},{"title":"세븐틴이 되고 싶습니다","contents":"2023.11.27","link":"https://magazine.weverse.io/article/view?lang=ko&colca=6&artist=&searchword=&num=950","retrieved":1701068908164,"image":"https://cdn-contents.magazine.weverse.io/upload/img/202311/20231124TyEkblUClD_.jpg"},{"title":"16년 차 ‘일잘러’ 아이돌 키의 인생","contents":"2023.11.27","link":"https://magazine.weverse.io/article/view?lang=ko&colca=6&artist=&searchword=&num=949","retrieved":1701054544685,"image":"https://cdn-contents.magazine.weverse.io/upload/img/202311/20231124i3O0A2qvugB.jpg"},{"title":"하이브가 ‘더 데뷔: 드림아카데미’ 출연자들 트레이닝 시키는 법","contents":"2023.11.24","link":"https://magazine.weverse.io/article/view?lang=ko&colca=6&artist=&searchword=&num=948","retrieved":1700809699640,"image":"https://cdn-contents.magazine.weverse.io/upload/img/202311/202311228fqyvZoI6.gif"},{"title":"팝스타로서의 정국이 보여준 것","contents":"2023.11.23","link":"https://magazine.weverse.io/article/view?lang=ko&colca=6&artist=&searchword=&num=947","retrieved":1700708896302,"image":"https://cdn-contents.magazine.weverse.io/upload/img/202311/20231121CV_5hSt.jpg"},{"title":"SEVENTEEN’s MOMENT: 호시와 김치","contents":"2023.11.22","link":"https://magazine.weverse.io/article/view?lang=ko&colca=6&artist=&searchword=&num=945","retrieved":1700622542738,"image":"https://cdn-contents.magazine.weverse.io/upload/img/202311/20231121DTBJbJV.jpg"},{"title":"&TEAM 콘텐츠 시청 가이드","contents":"2023.11.20","link":"https://magazine.weverse.io/article/view?lang=ko&colca=6&artist=&searchword=&num=943","retrieved":1700449735713,"image":"https://cdn-contents.magazine.weverse.io/upload/img/202311/20231117HmHpBZT.jpg"},{"title":"효진이 말하는 온앤오프의 2막","contents":"2023.10.31","link":"https://magazine.weverse.io/article/view?lang=ko&colca=6&artist=&searchword=&num=929","retrieved":1698721720250,"image":"https://cdn-contents.magazine.weverse.io/upload/img/202310/20231030hMB5r70T.jpg"},{"title":"테일러 스위프트가 ‘SNL’에서 전한 메시지","contents":"2023.10.30","link":"https://magazine.weverse.io/article/view?lang=ko&colca=6&artist=&searchword=&num=928","retrieved":1698635369919,"image":"https://cdn-contents.magazine.weverse.io/upload/img/202310/2023102771BhFcIVG000.jpg"},{"title":"니키의 인생 속 야구 이야기","contents":"2023.10.10","link":"https://magazine.weverse.io/article/view?lang=ko&colca=6&artist=&searchword=&num=893","retrieved":1696907329723,"image":"https://cdn-contents.magazine.weverse.io/upload/img/202310/20231010CJcvUhBf6e.gif"}]}