{"title":"Weverse Magazine ─ FEATURE","url":"https://magazine.weverse.io/article/list?lang=ko&colca=6","favicon":"https://ssl.pstatic.net/static/wevweb/public/favicon.ico","elements":[{"title":"지금 올리비아 로드리고를 이해하고 싶다면","contents":"2022.09.15","link":"https://magazine.weverse.io/article/view?lang=ko&colca=6&artist=&searchword=&num=528","retrieved":1663213339464,"image":"https://cdn-contents.magazine.weverse.io/upload/img/202209/20220914qqTR0KY.jpg"},{"title":"투모로우바이투게더 ‘ACT : LOVE SICK’ 투어 리포트","contents":"2022.09.13","link":"https://magazine.weverse.io/article/view?lang=ko&colca=6&artist=&searchword=&num=527","retrieved":1663054228718,"image":"https://cdn-contents.magazine.weverse.io/upload/img/202209/20220907Waf1oFOQR4.png"},{"title":"지난 여름 한국의 극장에서 일어난 일","contents":"2022.09.06","link":"https://magazine.weverse.io/article/view?lang=ko&colca=6&artist=&searchword=&num=525","retrieved":1662435732301,"image":"https://cdn-contents.magazine.weverse.io/upload/img/202209/20220905ZagxlPl.png"},{"title":"2022, 지금의 틱톡과 K-팝","contents":"2022.09.05","link":"https://magazine.weverse.io/article/view?lang=ko&colca=6&artist=&searchword=&num=523","retrieved":1662348996938},{"title":"세븐틴의 ‘BE THE SUN’ 월드 투어 리포트","contents":"2022.09.01","link":"https://magazine.weverse.io/article/view?lang=ko&colca=6&artist=&searchword=&num=514","retrieved":1662002895601,"image":"https://cdn-contents.magazine.weverse.io/upload/img/202209/20220901LmZayx_N0FL5O.png"},{"title":"ENHYPEN FANTASY","contents":"2022.08.29","link":"https://magazine.weverse.io/article/view?lang=ko&colca=6&artist=&searchword=&num=510","retrieved":1661955036647,"image":"https://cdn-contents.magazine.weverse.io/upload/img/202208/20220829W2rs79WY.png"},{"title":"방탄소년단이 ‘인더숲’에서 함께한 7가지 놀이","contents":"2022.08.26","link":"https://magazine.weverse.io/article/view?lang=ko&colca=6&artist=&searchword=&num=508","retrieved":1661955036647,"image":"https://cdn-contents.magazine.weverse.io/upload/img/202208/20220825YbUqd2tmOMyj.png"},{"title":"위버스에서 알아두면 좋은 기능 10","contents":"2022.08.25","link":"https://magazine.weverse.io/article/view?lang=ko&colca=6&artist=&searchword=&num=506","retrieved":1661955036651,"image":"https://cdn-contents.magazine.weverse.io/upload/img/202208/20220823xInUlpo.jpg"},{"title":"제이의 요리 철학","contents":"2022.08.22","link":"https://magazine.weverse.io/article/view?lang=ko&colca=6&artist=&searchword=&num=503","retrieved":1661955036651,"image":"https://cdn-contents.magazine.weverse.io/upload/img/202208/20220822KafYv0iOlS.png"},{"title":"하이브가 ‘출장 십오야’에 왜 갔을까","contents":"2022.08.08","link":"https://magazine.weverse.io/article/view?lang=ko&colca=6&artist=&searchword=&num=498","retrieved":1661955036651,"image":"https://cdn-contents.magazine.weverse.io/upload/img/202208/20220805JCF2nnrrBwPj.jpg"}]}